mcp_zentao/__init__.py
mcp_zentao/constants.py
mcp_zentao/sk_mcp_server.py
mcp_zentao/client/__init__.py
mcp_zentao/client/base_client.py
mcp_zentao/client/bug_client.py
mcp_zentao/client/project_client.py
mcp_zentao/client/session_client.py
mcp_zentao/client/task_client.py
mcp_zentao/client/user_client.py
mcp_zentao/client/zentao_client.py
mcp_zentao/models/__init__.py
mcp_zentao/models/bug.py
mcp_zentao/models/common.py
mcp_zentao/models/pagination.py
mcp_zentao/models/project.py
mcp_zentao/models/session.py
mcp_zentao/models/task.py
mcp_zentao/models/user.py
mcp_zentao-1.0.0.dist-info/METADATA
mcp_zentao-1.0.0.dist-info/WHEEL
mcp_zentao-1.0.0.dist-info/entry_points.txt
mcp_zentao-1.0.0.dist-info/licenses/LICENSE
mcp_zentao-1.0.0.dist-info/RECORD
